README.md
setup.py
mne_ari/__init__.py
mne_ari/permutation.py
mne_ari.egg-info/PKG-INFO
mne_ari.egg-info/SOURCES.txt
mne_ari.egg-info/dependency_links.txt
mne_ari.egg-info/requires.txt
mne_ari.egg-info/top_level.txt
mne_ari/ari/__init__.py
mne_ari/ari/_permutation.py
mne_ari/ari/ari.py
mne_ari/ari/parametric.py
mne_ari/ari/permutation.py
mne_ari/ari/tests/__init__.py
mne_ari/ari/tests/test_hommel.py
mne_ari/tests/__init__.py
mne_ari/tests/test_ari.py
mne_ari/tests/test_permutations.py