Metadata-Version: 1.1
Name: mne-ari
Version: 0.1.2
Summary: All-Resolutions Inference for M/EEG
Home-page: https://github.com/john-veillette/mne-ari
Author: John Veillette
Author-email: johnv@uchicago.edu
License: BSD-3-Clause
Platform: UNKNOWN
Classifier: Intended Audience :: Science/Research
Classifier: Intended Audience :: Developers
Classifier: License :: OSI Approved
Classifier: Programming Language :: Python
Classifier: Topic :: Software Development
Classifier: Topic :: Scientific/Engineering
Classifier: Operating System :: Microsoft :: Windows
Classifier: Operating System :: POSIX
Classifier: Operating System :: Unix
Classifier: Operating System :: MacOS
Classifier: Programming Language :: Python :: 3
